sl4p/__init__.py
sl4p/sl4p_config.eg.json
sl4p/sl4p_config.eg_professional.json
sl4p/mconfigs/apps_cfg.json
sl4p/mconfigs/apps_default.json
sl4p/mconfigs/cfgf_default.json
sl4p/src/__init__.py
sl4p/src/api.py
sl4p/src/config.py
sl4p/src/const.py
sl4p/src/context.py
sl4p/src/decorators.py
sl4p/src/embedding.py
sl4p/src/getter.py
sl4p/src/stats_performance.py
sl4p/src/utils.py
sl4p-1.4.5.dist-info/METADATA
sl4p-1.4.5.dist-info/WHEEL
sl4p-1.4.5.dist-info/top_level.txt
sl4p-1.4.5.dist-info/RECORD
