Metadata-Version: 2.1
Name: sl4p
Version: 1.4.5
Summary: Simple logger for python. Easy configuration and Multiprocess supported.
Home-page: https://github.com/surfhawk/sl4p
Author: surfhawk
Author-email: surfhawk@naver.com
License: BSD
Classifier: Topic :: Utilities
Classifier: Topic :: System :: Logging
Classifier: Development Status :: 4 - Beta
Classifier: Programming Language :: Python :: 3.5
Requires-Python: >=3.0
Requires-Dist: psutil
Requires-Dist: colorlog (==6.9.0)
Requires-Dist: colorama
Requires-Dist: pywin32 ; platform_system == "Windows"
